{
    "core": {
        "dere_list": [
            {
                "name": "一ノ瀬志希",
                "kana": "いちのせしき",
                "type": "cute",
                "models": [
                    "ミスティックエリクシル",
                    "インビテーション・ダイブ"
                ],
                "units": [
                    "lipps"
                ]
            },
            {
                "name": "鷺沢文香",
                "kana": "さぎさわふみか",
                "type": "cool",
                "models": [
                    "ブライトメモリーズ",
                    "密やかな饗宴"
                ],
                "units": [
                    "ainferia",
                    "caerula"
                ]
            },
            {
                "name": "城ヶ崎美嘉",
                "kana": "じょうがさきみか",
                "type": "passion",
                "models": [
                    "ハート★オーバーフロー",
                    "グロリアス★グロウ"
                ],
                "units": [
                    "lipps",
                    "hp"
                ]
            }
        ],
        "type_list": {
            "cute": [
                "一ノ瀬志希",
                "島村卯月",
                "小日向美穂"
            ],
            "cool": [
                "鷺沢文香",
                "渋谷凛",
                "神崎蘭子"
            ],
            "passion": [
                "城ヶ崎美嘉",
                "本田未央",
                "城ヶ崎莉嘉"
            ]
        },
        "unit_list": {
            "lipps": {
                "name": "Lipps",
                "kana": "りっぷす",
                "members": [
                    "塩見周子",
                    "一ノ瀬志希",
                    "速水奏",
                    "城ヶ崎美嘉",
                    "宮本フレデリカ"
                ],
                "tl": "塩見周子",
                "songs": [
                    "Tulip"
                ],
                "type": "tricolore"
            },
            "ainferia": {
                "name": "アインフェリア",
                "kana": "あいんふぇりあ",
                "members": [
                    "新田美波",
                    "高森藍子",
                    "橘ありす",
                    "鷺沢文香",
                    "相葉夕美"
                ],
                "tl": "新田美波",
                "songs": [
                    "生存本能ヴァルキュリア"
                ],
                "type": "cool"
            },
            "hp": {
                "name": "Happy Princess",
                "kana": "はっぴーぷりんせす",
                "members": [
                    "小日向美穂",
                    "城ヶ崎美嘉"
                ],
                "tl": "小日向美穂",
                "songs": [
                    "Shabon Song"
                ],
                "type": "tricolore"
            }
        }
    },
    "user": {}
}